{
    "diagrams": [
        {
            "id": "450",
            "topic": "Legal Logic",
            "category": "Law/Philosophy",
            "description": "A flowchart showing the fundamental concepts and structure of Legal Logic.",
            "diagram_type": "flowchart",
            "mermaid_code": "flowchart TD\n    LegalLogic[Legal Logic] --> Field1[Law]\n    LegalLogic --> Field2[Philosophy]\n    LegalLogic --> Integration[Integration Areas]\n    law --> lawSub1[Theory]\n    law --> lawSub2[Practice]\n    philosophy --> philosophySub1[Theory]\n    philosophy --> philosophySub2[Practice]\n    Integration --> Methods[Research Methods]\n    Integration --> Applications[Applications]",
            "complexity": "high",
            "tags": [
                "legal_logic",
                "law",
                "philosophy"
            ],
            "creation_date": "2025-11-04"
        }
    ]
}