{
    "diagrams": [
        {
            "id": "153",
            "topic": "Cultural Studies",
            "category": "Social Sciences",
            "description": "A timeline showing the development of Cultural Studies from Birmingham School to global cultural analysis.",
            "diagram_type": "timeline",
            "mermaid_code": "timeline\n    title Development of Cultural Studies\n    1964 : Birmingham Centre founded\n          : Hoggart and Williams\n          : Cultural studies begins\n    1970s : Hall's encoding/decoding\n          : Active audiences\n          : Media reception\n    1980s : Postcolonial theory\n          : Said's Orientalism\n          : Cultural imperialism\n    1990s : Identity politics\n          : Cultural identity\n          : Hybridity\n    2000s : Globalization studies\n          : Cultural flows\n          : Transnational culture\n    2010s : Digital culture\n          : Online communities\n          : Social media culture\n    2020s : Platform studies\n          : Algorithmic culture\n          : Digital capitalism",
            "complexity": "high",
            "tags": [
                "cultural_studies",
                "social_sciences"
            ],
            "creation_date": "2025-01-27"
        }
    ]
}
