{
    "diagrams": [
        {
            "id": "050",
            "topic": "Software Development",
            "category": "Computer Science",
            "description": "A mindmap showing the fundamental concepts and structure of Software Development.",
            "diagram_type": "mindmap",
            "mermaid_code": "mindmap\n  root((Software Development))\n    Programming Paradigms\n      Object-oriented\n      Functional\n      Procedural\n      Declarative\n    Development Methodologies\n      Agile\n      Scrum\n      Waterfall\n      DevOps\n    Version Control\n      Git\n      Branching Strategies\n      Collaboration\n      Code Review\n    Testing\n      Unit Testing\n      Integration Testing\n      System Testing\n      Test Automation\n    Software Architecture\n      Design Patterns\n      Microservices\n      Monolithic\n      Event-driven\n    Tools\n      IDEs\n      Debuggers\n      Profilers\n      CI/CD Pipelines\n    Best Practices\n      Code Quality\n      Documentation\n      Refactoring\n      Technical Debt",
            "complexity": "high",
            "tags": [
                "software_development",
                "computer_science"
            ],
            "creation_date": "2025-11-04"
        }
    ]
}

