{
    "diagrams": [
        {
            "id": "492",
            "topic": "Information Architecture",
            "category": "Design/Computer Science",
            "description": "A mindmap showing the fundamental concepts and structure of Information Architecture.",
            "diagram_type": "mindmap",
            "mermaid_code": "mindmap\n  root((Information<br/>Architecture))\n    Definition\n      Organizing information effectively\n      Findability and understanding\n    Components\n      Organization Systems\n        Hierarchical\n        Sequential\n        Matrix\n      Labeling Systems\n        Naming conventions\n        Terminology\n      Navigation Systems\n        Global\n        Local\n        Contextual\n      Search Systems\n        Queries\n        Filters\n        Results\n    Principles\n      Objects\n        Content types\n      Choices\n        Navigation options\n      Disclosure\n        Progressive\n    Methods\n      Card Sorting\n        Open\n        Closed\n      Tree Testing\n        Findability\n      Content Inventory\n        Audit\n      User Research\n        Mental models\n    Deliverables\n      Sitemaps\n        Structure\n        Hierarchy\n      Wireframes\n        Layout\n        Flow\n      Taxonomies\n        Categories\n        Tags\n      Controlled Vocabularies\n    Best Practices\n      User-Centered\n        Match mental models\n      Scalable\n        Future growth\n      Flexible\n        Multiple paths\n      Consistent\n        Predictable\n    Applications\n      Websites\n      Intranets\n      Mobile Apps\n      Software\n      Libraries\n    Challenges\n      Growing Content\n      Multiple Audiences\n      Complex Domains\n      Legacy Systems",
            "complexity": "high",
            "tags": [
                "information_architecture",
                "design",
                "computer_science"
            ],
            "creation_date": "2025-11-04"
        }
    ]
}

