{
  "diagrams": [
    {
      "id": "178",
      "topic": "Renaissance Art",
      "category": "Art",
      "description": "A flowchart showing the fundamental concepts of Renaissance Art.",
      "diagram_type": "flowchart",
      "mermaid_code": "flowchart TD\n    RenaissanceArt[Renaissance Art] --> EarlyRenaissance[Early Renaissance]\n    RenaissanceArt --> HighRenaissance[High Renaissance]\n    RenaissanceArt --> Northern[Northern Renaissance]\n    EarlyRenaissance --> Botticelli[Botticelli]\n    HighRenaissance --> Leonardo[Leonardo da Vinci]\n    HighRenaissance --> Michelangelo[Michelangelo]\n    HighRenaissance --> Raphael[Raphael]\n    Northern --> VanEyck[Van Eyck]\n    Northern --> Durer[Durer]",
      "complexity": "medium",
      "tags": [
        "renaissance art",
        "art"
      ],
      "creation_date": "2024-03-15"
    }
  ]
}