{
    "diagrams": [
        {
            "id": "102",
            "topic": "Public Health",
            "category": "Medicine",
            "description": "A flowchart illustrating the process of a public health intervention.",
            "diagram_type": "flowchart",
            "mermaid_code": "flowchart TD\n    A(Identify Public Health Problem) --> B(Needs Assessment);\n    B --> C(Develop Intervention);\n    C --> D(Implement Intervention);\n    D --> E(Monitor and Evaluate Intervention);\n    E --> F(Disseminate Findings);",
            "complexity": "medium",
            "tags": ["public_health", "medicine", "intervention", "program_planning", "evaluation"],
            "creation_date": "2024-01-16"
        }
    ]
}
