{
    "diagrams": [
        {
            "id": "108",
            "topic": "Sociology of Education",
            "category": "Sociology",
            "description": "A flowchart showing the fundamental concepts of Sociology of Education.",
            "diagram_type": "flowchart",
            "mermaid_code": "flowchart TD\n    SE[Sociology of Education] --> F[Functions of Education]\n    SE --> I[Inequality in Education]\n    SE --> P[Processes in Schools]\n    SE --> R[Reform & Policy]\n\n    F --> SOC[Socialization]\n    F --> CUL[Cultural Transmission]\n    F --> SORT[Sorting & Allocation]\n    F --> SKILL[Skill Development]\n\n    I --> CLASS[Social Class]\n    I --> RACE[Race & Ethnicity]\n    I --> GENDER[Gender]\n    \n    P --> CURR[Curriculum]\n    P --> INTER[Teacher-Student Interaction]\n    P --> PEER[Peer Groups]\n    \n    R --> STAND[Standardization]\n    R --> CHOICE[School Choice]\n    R --> FUND[Funding]",
            "complexity": "medium",
            "tags": [
                "sociology of education",
                "sociology"
            ],
            "creation_date": "2024-03-15"
        }
    ]
}
