{
    "diagrams": [
        {
            "id": "110",
            "topic": "Developmental Psychology",
            "category": "Psychology",
            "description": "A flowchart showing the fundamental concepts of Developmental Psychology.",
            "diagram_type": "flowchart",
            "mermaid_code": "flowchart TD\n    DP[Developmental Psychology] --> T[Theories]\n    DP --> P[Periods of Development]\n    DP --> D[Domains of Development]\n\n    T --> PSY[Psychoanalytic]\n    T --> COG[Cognitive]\n    T --> BEH[Behavioral]\n    T --> SOC[Sociocultural]\n\n    P --> PRE[Prenatal]\n    P --> INF[Infancy]\n    P --> CHILD[Childhood]\n    P --> ADO[Adolescence]\n    P --> ADULT[Adulthood]\n\n    D --> PHY[Physical]\n    D --> COG2[Cognitive]\n    D --> SOC2[Social/Emotional]",
            "complexity": "medium",
            "tags": [
                "developmental psychology",
                "psychology"
            ],
            "creation_date": "2024-03-15"
        }
    ]
}
