{
    "diagrams": [
        {
            "id": "080",
            "topic": "Cybersecurity",
            "category": "technology",
            "description": "A flowchart showing the fundamental concepts of Cybersecurity.",
            "diagram_type": "flowchart",
            "mermaid_code": "flowchart TD\n    Cybersecurity --> Principles[Core Principles]\n    Cybersecurity --> Domains[Security Domains]\n    Cybersecurity --> Threats[Cyber Threats]\n    Cybersecurity --> Countermeasures[Countermeasures]\n    Cybersecurity --> Frameworks[Frameworks & Compliance]\n\n    Principles --> CIA[Confidentiality, Integrity, Availability]\n    Principles --> NonRepudiation[Non-Repudiation]\n    Principles --> Authentication[Authentication]\n    Principles --> Authorization[Authorization]\n\n    Domains --> Network[Network Security]\n    Domains --> App[Application Security]\n    Domains --> Cloud[Cloud Security]\n    Domains --> IoT[IoT Security]\n    Domains --> Endpoint[Endpoint Security]\n\n    Threats --> Malware[Malware]\n    Threats --> Phishing[Phishing]\n    Threats --> Ransomware[Ransomware]\n    Threats --> SocialEng[Social Engineering]\n    Threats --> APTs[Advanced Persistent Threats]\n\n    Countermeasures --> Prevention[Prevention]\n    Countermeasures --> Detection[Detection]\n    Countermeasures --> Response[Incident Response]\n\n    Prevention --> Firewalls[Firewalls]\n    Prevention --> AV[Antivirus]\n    Prevention --> Encryption[Encryption]\n    Prevention --> IAM[Identity & Access Management]\n\n    Detection --> IDS_IPS[IDS/IPS]\n    Detection --> SIEM[SIEM]\n\n    Frameworks --> NIST[NIST Cybersecurity Framework]\n    Frameworks --> ISO27001[ISO/IEC 27001]\n    Frameworks --> GDPR[GDPR]\n    Frameworks --> HIPAA[HIPAA]",
            "complexity": "medium",
            "tags": ["cybersecurity", "technology", "computer_security", "nist", "gdpr"],
            "creation_date": "2024-01-16"
        }
    ]
}
