{
    "diagrams": [
        {
            "id": "123",
            "topic": "Public Administration",
            "category": "Political Science",
            "description": "A mindmap showing the fundamental concepts and structure of Public Administration.",
            "diagram_type": "mindmap",
            "mermaid_code": "mindmap\n  root((Public Administration))\n    Public Policy\n      Policy Making\n      Policy Analysis\n      Implementation\n      Evaluation\n    Public Management\n      Budgeting\n      Human Resources\n      Performance Management\n    Governance\n      Bureaucracy\n      Accountability\n      Transparency\n      Ethics\n    Reform\n      New Public Management\n      Digital Government\n      E-Governance",
            "complexity": "high",
            "tags": [
                "public_administration",
                "political_science"
            ],
            "creation_date": "2025-11-04"
        }
    ]
}

