{
    "diagrams": [
        {
            "id": "134",
            "topic": "Criminology",
            "category": "Law/Sociology",
            "description": "A mindmap showing the fundamental concepts and structure of Criminology.",
            "diagram_type": "mindmap",
            "mermaid_code": "mindmap\n  root((Criminology))\n    Theories of Crime\n      Classical Criminology\n      Positivist Criminology\n      Sociological Theories\n      Psychological Theories\n    Types of Crime\n      Street Crime\n      White Collar Crime\n      Organized Crime\n      Cybercrime\n    Criminal Justice System\n      Policing\n      Courts\n      Corrections\n      Rehabilitation\n    Research Methods\n      Crime Statistics\n      Victimization Surveys\n      Ethnography",
            "complexity": "high",
            "tags": [
                "criminology",
                "law",
                "sociology"
            ],
            "creation_date": "2025-11-04"
        }
    ]
}

