{
    "diagrams": [
        {
            "id": "301",
            "topic": "Hydrology",
            "category": "Earth Sciences",
            "description": "A detailed flowchart illustrating the global hydrological cycle, including storages and fluxes.",
            "diagram_type": "flowchart",
            "mermaid_code": "flowchart TD\n    subgraph \"Atmosphere\"\n        A[Atmospheric Water Vapor]\n    end\n\n    subgraph \"Surface\"\n        O[Oceans]\n        L[Lakes & Rivers]\n        G[Glaciers & Ice Caps]\n        GW[Groundwater]\n    end\n\n    O -- Evaporation --> A\n    L -- Evaporation --> A\n    G -- Sublimation --> A\n\n    A -- Condensation --> C[Clouds]\n    C -- Precipitation --> O & L & G & GW\n\n    L -- Surface Runoff --> O\n    GW -- Groundwater Flow --> O & L\n\n    G -- Melting --> L\n\n    subgraph \"Biosphere Interaction\"\n        P[Plants] -- Transpiration --> A\n        P -- Infiltration --> GW\n    end\n\n    C -- Precipitation --> P\n    L & GW --> P",
            "complexity": "high",
            "tags": ["hydrology", "earth_sciences", "hydrological_cycle", "water", "evaporation", "precipitation"],
            "creation_date": "2024-03-15"
        }
    ]
}
