{
    "diagrams": [
        {
            "id": "292",
            "topic": "Biological Conservation",
            "category": "Environmental Sciences",
            "description": "Biological Conservation encompasses multiple levels and approaches. Biodiversity levels include genetic diversity (within-species variation, population genetics, evolutionary potential), species diversity (taxonomic richness, endemism, flagship and indicator species), and ecosystem diversity (habitat types, biome representation, functional diversity). Major threats feature habitat destruction (deforestation, urbanization, agricultural expansion), fragmentation (patch isolation, edge effects, connectivity loss), overexploitation (overfishing, poaching, unsustainable harvesting), invasive species (competitive exclusion, predation, disease introduction), pollution (pesticides, plastics, nutrient loading), and climate change (range shifts, phenological mismatches, extreme events). Conservation approaches include in-situ conservation (protected areas like national parks and wildlife reserves, wildlife corridors, marine protected areas, community conservancies), ex-situ conservation (zoos and aquariums, botanical gardens, seed banks, captive breeding programs, cryopreservation), and restoration ecology (habitat restoration, reintroduction programs, rewilding, ecosystem rehabilitation). Conservation tools involve systematic conservation planning (gap analysis, priority setting, Marxan software), population viability analysis (PVA), genetic rescue, environmental DNA (eDNA) monitoring, and remote sensing. International frameworks include IUCN Red List categories, Convention on Biological Diversity (CBD), CITES (trade regulations), Ramsar Convention (wetlands), and UNESCO World Heritage Sites. Emerging concepts feature conservation genetics, landscape connectivity modeling, climate-adaptive conservation, nature-based solutions, reconciliation ecology, conservation technology (camera traps, drones, AI species identification), and One Health approaches integrating human, animal, and environmental health.",
            "diagram_type": "mindmap",
            "mermaid_code": "mindmap\n  root((<b>Biological<br>Conservation</b>))\n    <b>Biodiversity Levels</b>\n      Genetic Diversity\n        Within-species Variation\n        Population Genetics\n        Evolutionary Potential\n      Species Diversity\n        Taxonomic Richness\n        Endemism\n        Flagship Species\n        Indicator Species\n      Ecosystem Diversity\n        Habitat Types\n        Biome Representation\n        Functional Diversity\n    <b>Major Threats</b>\n      Habitat Destruction\n        Deforestation\n        Urbanization\n        Agricultural Expansion\n      Fragmentation\n        Patch Isolation\n        Edge Effects\n        Connectivity Loss\n      Overexploitation\n        Overfishing\n        Poaching\n        Unsustainable Harvest\n      Invasive Species\n        Competition\n        Predation\n        Disease Introduction\n      Pollution\n        Pesticides\n        Plastics\n        Nutrient Loading\n      Climate Change\n        Range Shifts\n        Phenological Mismatches\n        Extreme Events\n    <b>Conservation Approaches</b>\n      In-situ Conservation\n        Protected Areas\n          National Parks\n          Wildlife Reserves\n        Wildlife Corridors\n        Marine Protected Areas\n        Community Conservancies\n      Ex-situ Conservation\n        Zoos & Aquariums\n        Botanical Gardens\n        Seed Banks\n        Captive Breeding\n        Cryopreservation\n      Restoration Ecology\n        Habitat Restoration\n        Reintroduction Programs\n        Rewilding\n        Ecosystem Rehabilitation\n    <b>Conservation Tools</b>\n      Systematic Planning\n        Gap Analysis\n        Priority Setting\n        Marxan Software\n      Population Viability Analysis\n      Genetic Rescue\n      eDNA Monitoring\n      Remote Sensing\n    <b>International Frameworks</b>\n      IUCN Red List\n      Convention on Biological Diversity\n      CITES\n      Ramsar Convention\n      UNESCO World Heritage\n    <b>Emerging Concepts</b>\n      Conservation Genetics\n      Landscape Connectivity\n      Climate-adaptive Conservation\n      Nature-based Solutions\n      Reconciliation Ecology\n      Conservation Technology\n        Camera Traps\n        Drones\n        AI Identification\n      One Health",
            "complexity": "high",
            "tags": [
                "biological_conservation",
                "environmental_sciences"
            ],
            "creation_date": "2025-11-04"
        }
    ]
}